codingTracker/__init__.py
codingTracker/__main__.py
codingTracker/client.py
codingTracker/connexion.py
codingTracker/data.py
codingTracker/datahandler.py
codingTracker/process.py
codingTracker/server.py
codingTracker/setup_app.py
codingTracker-0.0.2.dist-info/METADATA
codingTracker-0.0.2.dist-info/WHEEL
codingTracker-0.0.2.dist-info/entry_points.txt
codingTracker-0.0.2.dist-info/top_level.txt
codingTracker-0.0.2.dist-info/RECORD
